paymob/__init__.py
paymob/auth.py
paymob/client.py
paymob/kiosk.py
paymob/orders.py
paymob/payment_keys.py
paymob/refund.py
paymob/transactions.py
paymob/wallet.py
paymob_sdk-1.0.1.dist-info/METADATA
paymob_sdk-1.0.1.dist-info/WHEEL
paymob_sdk-1.0.1.dist-info/top_level.txt
paymob_sdk-1.0.1.dist-info/RECORD
