Metadata-Version: 2.4
Name: paymob_sdk
Version: 1.0.1
Author: Youssef
Requires-Dist: urllib3
Dynamic: author
Dynamic: description
Dynamic: description-content-type
Dynamic: requires-dist
